beets_web2-0.2.1.dist-info/DESCRIPTION.rst
beets_web2-0.2.1.dist-info/METADATA
beets_web2-0.2.1.dist-info/RECORD
beets_web2-0.2.1.dist-info/WHEEL
beets_web2-0.2.1.dist-info/metadata.json
beets_web2-0.2.1.dist-info/top_level.txt
beetsplug/__init__.py
beetsplug/web2.py
