Metadata-Version: 2.0
Name: beets-web2
Version: 0.2.1
Summary: alternate web API using Bottle.py
Home-page: UNKNOWN
Author: Martin Zimmermann
Author-email: info@posativ.org
License: MIT
Platform: UNKNOWN
Classifier: License :: OSI Approved :: MIT License
Classifier: Programming Language :: Python :: 2
Classifier: Programming Language :: Python :: 2.7
Requires-Dist: bottle (>=0.12)
Provides-Extra: waitress
Requires-Dist: waitress; extra == 'waitress'
